LICENCE
MANIFEST.in
README.rst
setup.py
pyxpudpserver/XPlaneUDPServer.py
pyxpudpserver/__init__.py
pyxpudpserver.egg-info/PKG-INFO
pyxpudpserver.egg-info/SOURCES.txt
pyxpudpserver.egg-info/dependency_links.txt
pyxpudpserver.egg-info/not-zip-safe
pyxpudpserver.egg-info/top_level.txt